rtl/Synchronizer.v
module Synchronizer(
    input [3:0] Row,
    input clock,
    input reset,
    output reg S_Row
    );
    reg A_Row;
    
    always @ (negedge clock or posedge reset)
    begin
    if (reset) 
    begin 
    A_Row <= 0;
    S_Row <= 0;
    end
    else 
    begin 
    A_Row <= (Row[0] || Row[1] || Row[2] || Row[3]);
    S_Row <= A_Row;
    end 
    end
        
endmodule

rtl/Row_Scanner.v
module Row_Scanner(                                                //Scans for row of the asserted key
    input [15:0] Key,
    input [3:0] Col,
    output reg [3:0] Row
    );
    
    always @(Key or Col) begin                                  //Combinational logic for key assertion
    Row[0] =  Key[0] && Col[0] || Key[1] && Col[1] || Key[2] && Col[2] || Key[3] && Col[3];
    Row[1] =  Key[4] && Col[0] || Key[5] && Col[1] || Key[6] && Col[2] || Key[7] && Col[3];
    Row[2] =  Key[8] && Col[0] || Key[9] && Col[1] || Key[10] && Col[2] || Key[11] && Col[3];
    Row[3] =  Key[12] && Col[0] || Key[13] && Col[1] || Key[14] && Col[2] || Key[15] && Col[3];
    end

endmodule

rtl/keypad_encoder.v
module keypad_encoder(
    input [3:0] Row,
    input S_Row,
    input clock,
    input reset,
    output reg [3:0] Code,
    output Valid,
    output reg [3:0] Col
    );
    
    reg [5: 0] state, next_state;
    
   // One-hot encoding
    parameter S_0 = 6'b000001, S_1 = 6'b000010, S_2 = 6'b000100;
    parameter S_3 = 6'b001000, S_4 = 6'b010000, S_5 = 6'b100000;
    assign Valid = ((state == S_1) || (state == S_2) || (state == S_3) || (state == S_4)) && Row;
    always @ (Row or Col)
    case ({Row, Col})
        8'b0001_0001: Code = 0; 
        8'b0001_0010: Code = 1;
        8'b0001_0100: Code = 2; 
        8'b0001_1000: Code = 3;
        8'b0010_0001: Code = 4; 
        8'b0010_0010: Code = 5;
        8'b0010_0100: Code = 6;
        8'b0010_1000: Code = 7;
        8'b0100_0001: Code = 8;
        8'b0100_0010: Code = 9;
        8'b0100_0100: Code = 10;        
        8'b0100_1000: Code = 11;        
        8'b1000_0001: Code = 12;        
        8'b1000_0010: Code = 13;        
        8'b1000_0100: Code = 14;        
        8'b1000_1000: Code = 15;        
        default: Code = 0;              
    endcase
    always @(posedge clock or posedge reset)
    if (reset) state <= S_0;
    else state <= next_state;
    always@ (state or S_Row or Row)     
    begin next_state = state; Col = 0;
    case (state)
        //Assert all columns
        S_0: begin Col = 15; if (S_Row) next_state =S_1; end
        //Assert column 0
        S_1: begin Col = 1; if (Row) next_state = S_5; else next_state = S_2; end
        //Assert column 1
        S_2: begin Col = 2; if (Row) next_state = S_5; else next_state = S_3; end
        // Assert column 2
        S_3: begin Col = 4; if (Row) next_state = S_5; else next_state= S_4; end
       // Assert column 3
        S_4: begin Col = 8; if (Row) next_state = S_5; else next_state = S_0; end
        // Assert all rows
        S_5: begin Col = 15; if (Row ==0) next_state = S_0; end
    endcase
    end
endmodule

tb/keypad_scanner_tb.v
`timescale 1ns / 1ps


module keypad_scanner_tb ();
    wire            [3:0] Code;
    wire            Valid;
    wire            [3:0] Col;
    wire            [3:0] Row;
    reg             clock, reset;
    reg             [15: 0] Key;
    reg             [39: 0] Pressed;
    parameter  [39: 0] Key_0 = "Key_0";
    parameter  [39: 0] Key_1 = "Key_1";
    parameter  [39: 0] Key_2 = "Key_2";
    parameter  [39: 0] Key_3 = "Key_3";
    parameter  [39: 0] Key_4 = "Key_4";
    parameter  [39: 0] Key_5 = "Key_5";
    parameter  [39: 0] Key_6 = "Key_6";
    parameter  [39: 0] Key_7 = "Key_7";
    parameter  [39: 0] Key_8 = "Key_8";
    parameter  [39: 0] Key_9 = "Key_9";
    parameter  [39: 0] Key_A = "Key_A"; 
    parameter  [39: 0] Key_B = "Key_B";
    parameter  [39: 0] Key_C = "Key_C"; 
    parameter  [39: 0] Key_D = "Key_D"; 
    parameter  [39: 0] Key_E = "Key_E";
    parameter  [39: 0] Key_F = "Key_F";
    parameter  [39: 0] None = "None";
    integer        j, k;
    always @(Key) 
    begin                                                   // "one-hot" code for pressed key
    case (Key)
        16'h0000: Pressed = None;
        16'h0001: Pressed = Key_0;              //Key = 0000 0000 0000 0001
        16'h0002: Pressed = Key_1;              //Key = 0000 0000 0000 0010
        16'h0004: Pressed = Key_2;              //Key = 0000 0000 0000 0100
        16'h0008: Pressed = Key_3;              //Key = 0000 0000 0000 1000
        16'h0010: Pressed = Key_4;
        16'h0020: Pressed = Key_5;
        16'h0040: Pressed = Key_6;
        16'h0080: Pressed = Key_7;
        16'h0100: Pressed = Key_8;
        16'h0200: Pressed = Key_9;
        16'h0400: Pressed = Key_A;
        16'h0800: Pressed = Key_B;
        16'h1000: Pressed = Key_C;
        16'h2000: Pressed = Key_D;
        16'h4000: Pressed = Key_E;
        16'h8000: Pressed = Key_F;
        default: Pressed = None;
    endcase
    end
    keypad_encoder M1( Row, S_Row, clock, reset, Code, Valid, Col);
    Row_Scanner M2(Key, Col, Row);
    Synchronizer M3(Row, clock, reset, S_Row);

    initial begin
    $dumpfile("dump.vcd");
    $dumpvars(0, keypad_scanner_tb);
end
    
    initial #2000 $finish;
    initial begin clock = 0; forever #5 clock = ~clock; end
    initial begin reset = 1; #10 reset = 0; end
    initial 
        begin 
            for (k = 0; k<= 1; k = k+1) 
                begin 
                    Key = 0;
                    #20
                    for (j = 0; j <= 16; j = j+1) 
                        begin
                            #20 Key[j] = 1; 
                            #60 Key = 0; 
                        end 
                end 
        end
endmodule

dump.vcd
$date
	Wed Jun 24 10:16:11 2026
$end
$version
	Icarus Verilog
$end
$timescale
	1ps
$end
$scope module keypad_scanner_tb $end
$var wire 1 ! Valid $end
$var wire 1 " S_Row $end
$var wire 4 # Row [3:0] $end
$var wire 4 $ Col [3:0] $end
$var wire 4 % Code [3:0] $end
$var parameter 40 & Key_0 $end
$var parameter 40 ' Key_1 $end
$var parameter 40 ( Key_2 $end
$var parameter 40 ) Key_3 $end
$var parameter 40 * Key_4 $end
$var parameter 40 + Key_5 $end
$var parameter 40 , Key_6 $end
$var parameter 40 - Key_7 $end
$var parameter 40 . Key_8 $end
$var parameter 40 / Key_9 $end
$var parameter 40 0 Key_A $end
$var parameter 40 1 Key_B $end
$var parameter 40 2 Key_C $end
$var parameter 40 3 Key_D $end
$var parameter 40 4 Key_E $end
$var parameter 40 5 Key_F $end
$var parameter 0 6 None $end
$var reg 16 7 Key [15:0] $end
$var reg 40 8 Pressed [39:0] $end
$var reg 1 9 clock $end
$var reg 1 : reset $end
$var integer 32 ; j [31:0] $end
$var integer 32 < k [31:0] $end
$scope module M1 $end
$var wire 1 ! Valid $end
$var wire 1 9 clock $end
$var wire 1 : reset $end
$var wire 1 " S_Row $end
$var wire 4 = Row [3:0] $end
$var parameter 6 > S_0 $end
$var parameter 6 ? S_1 $end
$var parameter 6 @ S_2 $end
$var parameter 6 A S_3 $end
$var parameter 6 B S_4 $end
$var parameter 6 C S_5 $end
$var reg 4 D Code [3:0] $end
$var reg 4 E Col [3:0] $end
$var reg 6 F next_state [5:0] $end
$var reg 6 G state [5:0] $end
$upscope $end
$scope module M2 $end
$var wire 4 H Col [3:0] $end
$var wire 16 I Key [15:0] $end
$var reg 4 J Row [3:0] $end
$upscope $end
$scope module M3 $end
$var wire 4 K Row [3:0] $end
$var wire 1 9 clock $end
$var wire 1 : reset $end
$var reg 1 L A_Row $end
$var reg 1 " S_Row $end
$upscope $end
$upscope $end
$enddefinitions $end
$comment Show the parameter values. $end
$dumpall
b100000 C
b10000 B
b1000 A
b100 @
b10 ?
b1 >
b 6
b100101101100101011110010101111101000110 5
b100101101100101011110010101111101000101 4
b100101101100101011110010101111101000100 3
b100101101100101011110010101111101000011 2
b100101101100101011110010101111101000010 1
b100101101100101011110010101111101000001 0
b100101101100101011110010101111100111001 /
b100101101100101011110010101111100111000 .
b100101101100101011110010101111100110111 -
b100101101100101011110010101111100110110 ,
b100101101100101011110010101111100110101 +
b100101101100101011110010101111100110100 *
b100101101100101011110010101111100110011 )
b100101101100101011110010101111100110010 (
b100101101100101011110010101111100110001 '
b100101101100101011110010101111100110000 &
$end
#0
$dumpvars
0L
b0 K
b0 J
b0 I
b1111 H
b1 G
b1 F
b1111 E
b0 D
b0 =
b0 <
bx ;
1:
09
b1001110011011110110111001100101 8
b0 7
b0 %
b1111 $
b0 #
0"
0!
$end
#5000
19
#10000
09
0:
#15000
19
#20000
09
b0 ;
#25000
19
#30000
09
#35000
19
#40000
1L
b1111 $
b1111 E
b1111 H
b1 #
b1 =
b1 J
b1 K
b100101101100101011110010101111100110000 8
09
b1 7
b1 I
#45000
19
#50000
b10 F
b1111 $
b1111 E
b1111 H
1"
09
#55000
1!
b100000 F
b1 $
b1 E
b1 H
b10 G
19
#60000
09
#65000
0!
b1111 $
b1111 E
b1111 H
b100000 G
19
#70000
09
#75000
19
#80000
09
#85000
19
#90000
09
#95000
19
#100000
0L
b1 F
b1111 $
b1111 E
b1111 H
b0 #
b0 =
b0 J
b0 K
b1001110011011110110111001100101 8
09
b1 ;
b0 7
b0 I
#105000
b10 F
b1111 $
b1111 E
b1111 H
b1 G
19
#110000
b1111 $
b1111 E
b1111 H
b1 F
0"
09
#115000
19
#120000
1L
b1111 $
b1111 E
b1111 H
b1 #
b1 =
b1 J
b1 K
b100101101100101011110010101111100110001 8
09
b10 7
b10 I
#125000
19
#130000
b10 F
b1111 $
b1111 E
b1111 H
1"
09
#135000
b0 #
b0 =
b0 J
b0 K
b100 F
b1 $
b1 E
b1 H
b10 G
19
#140000
0L
09
#145000
1!
b1 %
b1 D
b1 #
b1 =
b1 J
b1 K
b100000 F
b10 $
b10 E
b10 H
b100 G
19
#150000
b10 $
b10 E
b10 H
b100000 F
0"
1L
09
#155000
0!
b0 %
b0 D
b1111 $
b1111 E
b1111 H
b100000 G
19
#160000
b1111 $
b1111 E
b1111 H
1"
09
#165000
19
#170000
09
#175000
19
#180000
0L
b1 F
b1111 $
b1111 E
b1111 H
b0 #
b0 =
b0 J
b0 K
b1001110011011110110111001100101 8
09
b10 ;
b0 7
b0 I
#185000
b10 F
b1111 $
b1111 E
b1111 H
b1 G
19
#190000
b1111 $
b1111 E
b1111 H
b1 F
0"
09
#195000
19
#200000
1L
b1111 $
b1111 E
b1111 H
b1 #
b1 =
b1 J
b1 K
b100101101100101011110010101111100110010 8
09
b100 7
b100 I
#205000
19
#210000
b10 F
b1111 $
b1111 E
b1111 H
1"
09
#215000
b0 #
b0 =
b0 J
b0 K
b100 F
b1 $
b1 E
b1 H
b10 G
19
#220000
0L
09
#225000
b1000 F
b10 $
b10 E
b10 H
b100 G
19
#230000
b10 $
b10 E
b10 H
b1000 F
0"
09
#235000
1!
b10 %
b10 D
b1 #
b1 =
b1 J
b1 K
b100000 F
b100 $
b100 E
b100 H
b1000 G
19
#240000
1L
09
#245000
0!
b0 %
b0 D
b1111 $
b1111 E
b1111 H
b100000 G
19
#250000
b1111 $
b1111 E
b1111 H
1"
09
#255000
19
#260000
0L
b1 F
b1111 $
b1111 E
b1111 H
b0 #
b0 =
b0 J
b0 K
b1001110011011110110111001100101 8
09
b11 ;
b0 7
b0 I
#265000
b10 F
b1111 $
b1111 E
b1111 H
b1 G
19
#270000
b1111 $
b1111 E
b1111 H
b1 F
0"
09
#275000
19
#280000
1L
b1111 $
b1111 E
b1111 H
b1 #
b1 =
b1 J
b1 K
b100101101100101011110010101111100110011 8
09
b1000 7
b1000 I
#285000
19
#290000
b10 F
b1111 $
b1111 E
b1111 H
1"
09
#295000
b0 #
b0 =
b0 J
b0 K
b100 F
b1 $
b1 E
b1 H
b10 G
19
#300000
0L
09
#305000
b1000 F
b10 $
b10 E
b10 H
b100 G
19
#310000
b10 $
b10 E
b10 H
b1000 F
0"
09
#315000
b10000 F
b100 $
b100 E
b100 H
b1000 G
19
#320000
09
#325000
1!
b11 %
b11 D
b1 #
b1 =
b1 J
b1 K
b100000 F
b1000 $
b1000 E
b1000 H
b10000 G
19
#330000
1L
09
#335000
b0 %
b0 D
0!
b1111 $
b1111 E
b1111 H
b100000 G
19
#340000
1"
0L
b1 F
b1111 $
b1111 E
b1111 H
b0 #
b0 =
b0 J
b0 K
b1001110011011110110111001100101 8
09
b100 ;
b0 7
b0 I
#345000
b10 F
b1111 $
b1111 E
b1111 H
b1 G
19
#350000
b1111 $
b1111 E
b1111 H
b1 F
0"
09
#355000
19
#360000
1L
b1111 $
b1111 E
b1111 H
b10 #
b10 =
b10 J
b10 K
b100101101100101011110010101111100110100 8
09
b10000 7
b10000 I
#365000
19
#370000
b10 F
b1111 $
b1111 E
b1111 H
1"
09
#375000
1!
b100 %
b100 D
b100000 F
b1 $
b1 E
b1 H
b10 G
19
#380000
09
#385000
0!
b0 %
b0 D
b1111 $
b1111 E
b1111 H
b100000 G
19
#390000
09
#395000
19
#400000
09
#405000
19
#410000
09
#415000
19
#420000
0L
b1 F
b1111 $
b1111 E
b1111 H
b0 #
b0 =
b0 J
b0 K
b1001110011011110110111001100101 8
09
b101 ;
b0 7
b0 I
#425000
b10 F
b1111 $
b1111 E
b1111 H
b1 G
19
#430000
b1111 $
b1111 E
b1111 H
b1 F
0"
09
#435000
19
#440000
1L
b1111 $
b1111 E
b1111 H
b10 #
b10 =
b10 J
b10 K
b100101101100101011110010101111100110101 8
09
b100000 7
b100000 I
#445000
19
#450000
b10 F
b1111 $
b1111 E
b1111 H
1"
09
#455000
b0 #
b0 =
b0 J
b0 K
b100 F
b1 $
b1 E
b1 H
b10 G
19
#460000
0L
09
#465000
1!
b101 %
b101 D
b10 #
b10 =
b10 J
b10 K
b100000 F
b10 $
b10 E
b10 H
b100 G
19
#470000
b10 $
b10 E
b10 H
b100000 F
0"
1L
09
#475000
0!
b0 %
b0 D
b1111 $
b1111 E
b1111 H
b100000 G
19
#480000
b1111 $
b1111 E
b1111 H
1"
09
#485000
19
#490000
09
#495000
19
#500000
0L
b1 F
b1111 $
b1111 E
b1111 H
b0 #
b0 =
b0 J
b0 K
b1001110011011110110111001100101 8
09
b110 ;
b0 7
b0 I
#505000
b10 F
b1111 $
b1111 E
b1111 H
b1 G
19
#510000
b1111 $
b1111 E
b1111 H
b1 F
0"
09
#515000
19
#520000
1L
b1111 $
b1111 E
b1111 H
b10 #
b10 =
b10 J
b10 K
b100101101100101011110010101111100110110 8
09
b1000000 7
b1000000 I
#525000
19
#530000
b10 F
b1111 $
b1111 E
b1111 H
1"
09
#535000
b0 #
b0 =
b0 J
b0 K
b100 F
b1 $
b1 E
b1 H
b10 G
19
#540000
0L
09
#545000
b1000 F
b10 $
b10 E
b10 H
b100 G
19
#550000
b10 $
b10 E
b10 H
b1000 F
0"
09
#555000
1!
b110 %
b110 D
b10 #
b10 =
b10 J
b10 K
b100000 F
b100 $
b100 E
b100 H
b1000 G
19
#560000
1L
09
#565000
0!
b0 %
b0 D
b1111 $
b1111 E
b1111 H
b100000 G
19
#570000
b1111 $
b1111 E
b1111 H
1"
09
#575000
19
#580000
0L
b1 F
b1111 $
b1111 E
b1111 H
b0 #
b0 =
b0 J
b0 K
b1001110011011110110111001100101 8
09
b111 ;
b0 7
b0 I
#585000
b10 F
b1111 $
b1111 E
b1111 H
b1 G
19
#590000
b1111 $
b1111 E
b1111 H
b1 F
0"
09
#595000
19
#600000
1L
b1111 $
b1111 E
b1111 H
b10 #
b10 =
b10 J
b10 K
b100101101100101011110010101111100110111 8
09
b10000000 7
b10000000 I
#605000
19
#610000
b10 F
b1111 $
b1111 E
b1111 H
1"
09
#615000
b0 #
b0 =
b0 J
b0 K
b100 F
b1 $
b1 E
b1 H
b10 G
19
#620000
0L
09
#625000
b1000 F
b10 $
b10 E
b10 H
b100 G
19
#630000
b10 $
b10 E
b10 H
b1000 F
0"
09
#635000
b10000 F
b100 $
b100 E
b100 H
b1000 G
19
#640000
09
#645000
1!
b111 %
b111 D
b10 #
b10 =
b10 J
b10 K
b100000 F
b1000 $
b1000 E
b1000 H
b10000 G
19
#650000
1L
09
#655000
b0 %
b0 D
0!
b1111 $
b1111 E
b1111 H
b100000 G
19
#660000
1"
0L
b1 F
b1111 $
b1111 E
b1111 H
b0 #
b0 =
b0 J
b0 K
b1001110011011110110111001100101 8
09
b1000 ;
b0 7
b0 I
#665000
b10 F
b1111 $
b1111 E
b1111 H
b1 G
19
#670000
b1111 $
b1111 E
b1111 H
b1 F
0"
09
#675000
19
#680000
1L
b1111 $
b1111 E
b1111 H
b100 #
b100 =
b100 J
b100 K
b100101101100101011110010101111100111000 8
09
b100000000 7
b100000000 I
#685000
19
#690000
b10 F
b1111 $
b1111 E
b1111 H
1"
09
#695000
1!
b1000 %
b1000 D
b100000 F
b1 $
b1 E
b1 H
b10 G
19
#700000
09
#705000
0!
b0 %
b0 D
b1111 $
b1111 E
b1111 H
b100000 G
19
#710000
09
#715000
19
#720000
09
#725000
19
#730000
09
#735000
19
#740000
0L
b1 F
b1111 $
b1111 E
b1111 H
b0 #
b0 =
b0 J
b0 K
b1001110011011110110111001100101 8
09
b1001 ;
b0 7
b0 I
#745000
b10 F
b1111 $
b1111 E
b1111 H
b1 G
19
#750000
b1111 $
b1111 E
b1111 H
b1 F
0"
09
#755000
19
#760000
1L
b1111 $
b1111 E
b1111 H
b100 #
b100 =
b100 J
b100 K
b100101101100101011110010101111100111001 8
09
b1000000000 7
b1000000000 I
#765000
19
#770000
b10 F
b1111 $
b1111 E
b1111 H
1"
09
#775000
b0 #
b0 =
b0 J
b0 K
b100 F
b1 $
b1 E
b1 H
b10 G
19
#780000
0L
09
#785000
1!
b1001 %
b1001 D
b100 #
b100 =
b100 J
b100 K
b100000 F
b10 $
b10 E
b10 H
b100 G
19
#790000
b10 $
b10 E
b10 H
b100000 F
0"
1L
09
#795000
0!
b0 %
b0 D
b1111 $
b1111 E
b1111 H
b100000 G
19
#800000
b1111 $
b1111 E
b1111 H
1"
09
#805000
19
#810000
09
#815000
19
#820000
0L
b1 F
b1111 $
b1111 E
b1111 H
b0 #
b0 =
b0 J
b0 K
b1001110011011110110111001100101 8
09
b1010 ;
b0 7
b0 I
#825000
b10 F
b1111 $
b1111 E
b1111 H
b1 G
19
#830000
b1111 $
b1111 E
b1111 H
b1 F
0"
09
#835000
19
#840000
1L
b1111 $
b1111 E
b1111 H
b100 #
b100 =
b100 J
b100 K
b100101101100101011110010101111101000001 8
09
b10000000000 7
b10000000000 I
#845000
19
#850000
b10 F
b1111 $
b1111 E
b1111 H
1"
09
#855000
b0 #
b0 =
b0 J
b0 K
b100 F
b1 $
b1 E
b1 H
b10 G
19
#860000
0L
09
#865000
b1000 F
b10 $
b10 E
b10 H
b100 G
19
#870000
b10 $
b10 E
b10 H
b1000 F
0"
09
#875000
1!
b1010 %
b1010 D
b100 #
b100 =
b100 J
b100 K
b100000 F
b100 $
b100 E
b100 H
b1000 G
19
#880000
1L
09
#885000
0!
b0 %
b0 D
b1111 $
b1111 E
b1111 H
b100000 G
19
#890000
b1111 $
b1111 E
b1111 H
1"
09
#895000
19
#900000
0L
b1 F
b1111 $
b1111 E
b1111 H
b0 #
b0 =
b0 J
b0 K
b1001110011011110110111001100101 8
09
b1011 ;
b0 7
b0 I
#905000
b10 F
b1111 $
b1111 E
b1111 H
b1 G
19
#910000
b1111 $
b1111 E
b1111 H
b1 F
0"
09
#915000
19
#920000
1L
b1111 $
b1111 E
b1111 H
b100 #
b100 =
b100 J
b100 K
b100101101100101011110010101111101000010 8
09
b100000000000 7
b100000000000 I
#925000
19
#930000
b10 F
b1111 $
b1111 E
b1111 H
1"
09
#935000
b0 #
b0 =
b0 J
b0 K
b100 F
b1 $
b1 E
b1 H
b10 G
19
#940000
0L
09
#945000
b1000 F
b10 $
b10 E
b10 H
b100 G
19
#950000
b10 $
b10 E
b10 H
b1000 F
0"
09
#955000
b10000 F
b100 $
b100 E
b100 H
b1000 G
19
#960000
09
#965000
1!
b1011 %
b1011 D
b100 #
b100 =
b100 J
b100 K
b100000 F
b1000 $
b1000 E
b1000 H
b10000 G
19
#970000
1L
09
#975000
b0 %
b0 D
0!
b1111 $
b1111 E
b1111 H
b100000 G
19
#980000
1"
0L
b1 F
b1111 $
b1111 E
b1111 H
b0 #
b0 =
b0 J
b0 K
b1001110011011110110111001100101 8
09
b1100 ;
b0 7
b0 I
#985000
b10 F
b1111 $
b1111 E
b1111 H
b1 G
19
#990000
b1111 $
b1111 E
b1111 H
b1 F
0"
09
#995000
19
#1000000
1L
b1111 $
b1111 E
b1111 H
b1000 #
b1000 =
b1000 J
b1000 K
b100101101100101011110010101111101000011 8
09
b1000000000000 7
b1000000000000 I
#1005000
19
#1010000
b10 F
b1111 $
b1111 E
b1111 H
1"
09
#1015000
1!
b1100 %
b1100 D
b100000 F
b1 $
b1 E
b1 H
b10 G
19
#1020000
09
#1025000
0!
b0 %
b0 D
b1111 $
b1111 E
b1111 H
b100000 G
19
#1030000
09
#1035000
19
#1040000
09
#1045000
19
#1050000
09
#1055000
19
#1060000
0L
b1 F
b1111 $
b1111 E
b1111 H
b0 #
b0 =
b0 J
b0 K
b1001110011011110110111001100101 8
09
b1101 ;
b0 7
b0 I
#1065000
b10 F
b1111 $
b1111 E
b1111 H
b1 G
19
#1070000
b1111 $
b1111 E
b1111 H
b1 F
0"
09
#1075000
19
#1080000
1L
b1111 $
b1111 E
b1111 H
b1000 #
b1000 =
b1000 J
b1000 K
b100101101100101011110010101111101000100 8
09
b10000000000000 7
b10000000000000 I
#1085000
19
#1090000
b10 F
b1111 $
b1111 E
b1111 H
1"
09
#1095000
b0 #
b0 =
b0 J
b0 K
b100 F
b1 $
b1 E
b1 H
b10 G
19
#1100000
0L
09
#1105000
1!
b1101 %
b1101 D
b1000 #
b1000 =
b1000 J
b1000 K
b100000 F
b10 $
b10 E
b10 H
b100 G
19
#1110000
b10 $
b10 E
b10 H
b100000 F
0"
1L
09
#1115000
0!
b0 %
b0 D
b1111 $
b1111 E
b1111 H
b100000 G
19
#1120000
b1111 $
b1111 E
b1111 H
1"
09
#1125000
19
#1130000
09
#1135000
19
#1140000
0L
b1 F
b1111 $
b1111 E
b1111 H
b0 #
b0 =
b0 J
b0 K
b1001110011011110110111001100101 8
09
b1110 ;
b0 7
b0 I
#1145000
b10 F
b1111 $
b1111 E
b1111 H
b1 G
19
#1150000
b1111 $
b1111 E
b1111 H
b1 F
0"
09
#1155000
19
#1160000
1L
b1111 $
b1111 E
b1111 H
b1000 #
b1000 =
b1000 J
b1000 K
b100101101100101011110010101111101000101 8
09
b100000000000000 7
b100000000000000 I
#1165000
19
#1170000
b10 F
b1111 $
b1111 E
b1111 H
1"
09
#1175000
b0 #
b0 =
b0 J
b0 K
b100 F
b1 $
b1 E
b1 H
b10 G
19
#1180000
0L
09
#1185000
b1000 F
b10 $
b10 E
b10 H
b100 G
19
#1190000
b10 $
b10 E
b10 H
b1000 F
0"
09
#1195000
1!
b1110 %
b1110 D
b1000 #
b1000 =
b1000 J
b1000 K
b100000 F
b100 $
b100 E
b100 H
b1000 G
19
#1200000
1L
09
#1205000
0!
b0 %
b0 D
b1111 $
b1111 E
b1111 H
b100000 G
19
#1210000
b1111 $
b1111 E
b1111 H
1"
09
#1215000
19
#1220000
0L
b1 F
b1111 $
b1111 E
b1111 H
b0 #
b0 =
b0 J
b0 K
b1001110011011110110111001100101 8
09
b1111 ;
b0 7
b0 I
#1225000
b10 F
b1111 $
b1111 E
b1111 H
b1 G
19
#1230000
b1111 $
b1111 E
b1111 H
b1 F
0"
09
#1235000
19
#1240000
1L
b1111 $
b1111 E
b1111 H
b1000 #
b1000 =
b1000 J
b1000 K
b100101101100101011110010101111101000110 8
09
b1000000000000000 7
b1000000000000000 I
#1245000
19
#1250000
b10 F
b1111 $
b1111 E
b1111 H
1"
09
#1255000
b0 #
b0 =
b0 J
b0 K
b100 F
b1 $
b1 E
b1 H
b10 G
19
#1260000
0L
09
#1265000
b1000 F
b10 $
b10 E
b10 H
b100 G
19
#1270000
b10 $
b10 E
b10 H
b1000 F
0"
09
#1275000
b10000 F
b100 $
b100 E
b100 H
b1000 G
19
#1280000
09
#1285000
1!
b1111 %
b1111 D
b1000 #
b1000 =
b1000 J
b1000 K
b100000 F
b1000 $
b1000 E
b1000 H
b10000 G
19
#1290000
1L
09
#1295000
b0 %
b0 D
0!
b1111 $
b1111 E
b1111 H
b100000 G
19
#1300000
1"
0L
b1 F
b1111 $
b1111 E
b1111 H
b0 #
b0 =
b0 J
b0 K
b1001110011011110110111001100101 8
09
b10000 ;
b0 7
b0 I
#1305000
b10 F
b1111 $
b1111 E
b1111 H
b1 G
19
#1310000
b1111 $
b1111 E
b1111 H
b1 F
0"
09
#1315000
19
#1320000
09
#1325000
19
#1330000
09
#1335000
19
#1340000
09
#1345000
19
#1350000
09
#1355000
19
#1360000
09
#1365000
19
#1370000
09
#1375000
19
#1380000
09
b1 <
b10001 ;
#1385000
19
#1390000
09
#1395000
19
#1400000
09
b0 ;
#1405000
19
#1410000
09
#1415000
19
#1420000
1L
b1111 $
b1111 E
b1111 H
b1 #
b1 =
b1 J
b1 K
b100101101100101011110010101111100110000 8
09
b1 7
b1 I
#1425000
19
#1430000
b10 F
b1111 $
b1111 E
b1111 H
1"
09
#1435000
1!
b100000 F
b1 $
b1 E
b1 H
b10 G
19
#1440000
09
#1445000
0!
b1111 $
b1111 E
b1111 H
b100000 G
19
#1450000
09
#1455000
19
#1460000
09
#1465000
19
#1470000
09
#1475000
19
#1480000
0L
b1 F
b1111 $
b1111 E
b1111 H
b0 #
b0 =
b0 J
b0 K
b1001110011011110110111001100101 8
09
b1 ;
b0 7
b0 I
#1485000
b10 F
b1111 $
b1111 E
b1111 H
b1 G
19
#1490000
b1111 $
b1111 E
b1111 H
b1 F
0"
09
#1495000
19
#1500000
1L
b1111 $
b1111 E
b1111 H
b1 #
b1 =
b1 J
b1 K
b100101101100101011110010101111100110001 8
09
b10 7
b10 I
#1505000
19
#1510000
b10 F
b1111 $
b1111 E
b1111 H
1"
09
#1515000
b0 #
b0 =
b0 J
b0 K
b100 F
b1 $
b1 E
b1 H
b10 G
19
#1520000
0L
09
#1525000
1!
b1 %
b1 D
b1 #
b1 =
b1 J
b1 K
b100000 F
b10 $
b10 E
b10 H
b100 G
19
#1530000
b10 $
b10 E
b10 H
b100000 F
0"
1L
09
#1535000
0!
b0 %
b0 D
b1111 $
b1111 E
b1111 H
b100000 G
19
#1540000
b1111 $
b1111 E
b1111 H
1"
09
#1545000
19
#1550000
09
#1555000
19
#1560000
0L
b1 F
b1111 $
b1111 E
b1111 H
b0 #
b0 =
b0 J
b0 K
b1001110011011110110111001100101 8
09
b10 ;
b0 7
b0 I
#1565000
b10 F
b1111 $
b1111 E
b1111 H
b1 G
19
#1570000
b1111 $
b1111 E
b1111 H
b1 F
0"
09
#1575000
19
#1580000
1L
b1111 $
b1111 E
b1111 H
b1 #
b1 =
b1 J
b1 K
b100101101100101011110010101111100110010 8
09
b100 7
b100 I
#1585000
19
#1590000
b10 F
b1111 $
b1111 E
b1111 H
1"
09
#1595000
b0 #
b0 =
b0 J
b0 K
b100 F
b1 $
b1 E
b1 H
b10 G
19
#1600000
0L
09
#1605000
b1000 F
b10 $
b10 E
b10 H
b100 G
19
#1610000
b10 $
b10 E
b10 H
b1000 F
0"
09
#1615000
1!
b10 %
b10 D
b1 #
b1 =
b1 J
b1 K
b100000 F
b100 $
b100 E
b100 H
b1000 G
19
#1620000
1L
09
#1625000
0!
b0 %
b0 D
b1111 $
b1111 E
b1111 H
b100000 G
19
#1630000
b1111 $
b1111 E
b1111 H
1"
09
#1635000
19
#1640000
0L
b1 F
b1111 $
b1111 E
b1111 H
b0 #
b0 =
b0 J
b0 K
b1001110011011110110111001100101 8
09
b11 ;
b0 7
b0 I
#1645000
b10 F
b1111 $
b1111 E
b1111 H
b1 G
19
#1650000
b1111 $
b1111 E
b1111 H
b1 F
0"
09
#1655000
19
#1660000
1L
b1111 $
b1111 E
b1111 H
b1 #
b1 =
b1 J
b1 K
b100101101100101011110010101111100110011 8
09
b1000 7
b1000 I
#1665000
19
#1670000
b10 F
b1111 $
b1111 E
b1111 H
1"
09
#1675000
b0 #
b0 =
b0 J
b0 K
b100 F
b1 $
b1 E
b1 H
b10 G
19
#1680000
0L
09
#1685000
b1000 F
b10 $
b10 E
b10 H
b100 G
19
#1690000
b10 $
b10 E
b10 H
b1000 F
0"
09
#1695000
b10000 F
b100 $
b100 E
b100 H
b1000 G
19
#1700000
09
#1705000
1!
b11 %
b11 D
b1 #
b1 =
b1 J
b1 K
b100000 F
b1000 $
b1000 E
b1000 H
b10000 G
19
#1710000
1L
09
#1715000
b0 %
b0 D
0!
b1111 $
b1111 E
b1111 H
b100000 G
19
#1720000
1"
0L
b1 F
b1111 $
b1111 E
b1111 H
b0 #
b0 =
b0 J
b0 K
b1001110011011110110111001100101 8
09
b100 ;
b0 7
b0 I
#1725000
b10 F
b1111 $
b1111 E
b1111 H
b1 G
19
#1730000
b1111 $
b1111 E
b1111 H
b1 F
0"
09
#1735000
19
#1740000
1L
b1111 $
b1111 E
b1111 H
b10 #
b10 =
b10 J
b10 K
b100101101100101011110010101111100110100 8
09
b10000 7
b10000 I
#1745000
19
#1750000
b10 F
b1111 $
b1111 E
b1111 H
1"
09
#1755000
1!
b100 %
b100 D
b100000 F
b1 $
b1 E
b1 H
b10 G
19
#1760000
09
#1765000
0!
b0 %
b0 D
b1111 $
b1111 E
b1111 H
b100000 G
19
#1770000
09
#1775000
19
#1780000
09
#1785000
19
#1790000
09
#1795000
19
#1800000
0L
b1 F
b1111 $
b1111 E
b1111 H
b0 #
b0 =
b0 J
b0 K
b1001110011011110110111001100101 8
09
b101 ;
b0 7
b0 I
#1805000
b10 F
b1111 $
b1111 E
b1111 H
b1 G
19
